arkDLtools/__init__.py
arkDLtools/dltools.py
arkDLtools-0.24.7.8.dist-info/LICENSE
arkDLtools-0.24.7.8.dist-info/METADATA
arkDLtools-0.24.7.8.dist-info/NOTICE
arkDLtools-0.24.7.8.dist-info/WHEEL
arkDLtools-0.24.7.8.dist-info/top_level.txt
arkDLtools-0.24.7.8.dist-info/RECORD
