Metadata-Version: 2.1
Name: arkDLtools
Version: 0.24.7.8
Summary: A toolkit for use with pytorch. Self-contained imperative programming, highly customizable, comes with its own instruction controller oriented to complex processes (partly multithreaded parallel, partly sequential serial, and able to be nested). Has built-in features to instantly visualize the training process (highly customizable), generate logs, auto-save, pause and resume training, automatic device selection, etc., and thanks to the use of multi-threading, it has no impact on the tra
Author-email: arkhubs <1459826385@qq.com>
Project-URL: Homepage, https://github.com/arkhubs/llmFlight/tree/main/Scripts/arkDLtools
Project-URL: Bug Tracker, https://github.com/arkhubs/llmFlight/issues
Classifier: Programming Language :: Python :: 3
Classifier: License :: OSI Approved :: Apache Software License
Classifier: Operating System :: OS Independent
Requires-Python: >=3.7
License-File: LICENSE
License-File: NOTICE
Requires-Dist: pandas
Requires-Dist: matplotlib
